{
  "annotations": {
    "list": [
      {
        "builtIn": 1,
        "datasource": "-- Grafana --",
        "enable": true,
        "hide": true,
        "iconColor": "rgba(0, 211, 255, 1)",
        "name": "Annotations & Alerts",
        "type": "dashboard"
      }
    ]
  },
  "editable": true,
  "gnetId": null,
  "graphTooltip": 0,
  "id": null,
  "uid": "sting-pii",
  "links": [],
  "panels": [
    {
      "datasource": "Loki",
      "fieldConfig": {
        "defaults": {
          "color": {
            "mode": "thresholds"
          },
          "mappings": [],
          "thresholds": {
            "mode": "absolute",
            "steps": [
              {
                "color": "green",
                "value": null
              },
              {
                "color": "yellow",
                "value": 10
              },
              {
                "color": "red",
                "value": 50
              }
            ]
          }
        },
        "overrides": []
      },
      "gridPos": {
        "h": 8,
        "w": 8,
        "x": 0,
        "y": 0
      },
      "id": 1,
      "options": {
        "orientation": "auto",
        "reduceOptions": {
          "values": false,
          "calcs": [
            "lastNotNull"
          ],
          "fields": ""
        },
        "showThresholdLabels": false,
        "showThresholdMarkers": true
      },
      "pluginVersion": "11.0.0",
      "targets": [
        {
          "expr": "sum(count_over_time({service_name=~\".*\"} |~ \"(?i)pii.*detected\" [1h]))",
          "refId": "A"
        }
      ],
      "title": "PII Detections (Last Hour)",
      "type": "gauge"
    },
    {
      "datasource": "Loki",
      "fieldConfig": {
        "defaults": {
          "color": {
            "mode": "thresholds"
          },
          "mappings": [],
          "thresholds": {
            "mode": "absolute",
            "steps": [
              {
                "color": "green",
                "value": null
              },
              {
                "color": "yellow",
                "value": 20
              },
              {
                "color": "red",
                "value": 100
              }
            ]
          }
        },
        "overrides": []
      },
      "gridPos": {
        "h": 8,
        "w": 8,
        "x": 8,
        "y": 0
      },
      "id": 2,
      "options": {
        "orientation": "auto",
        "reduceOptions": {
          "values": false,
          "calcs": [
            "lastNotNull"
          ],
          "fields": ""
        },
        "showThresholdLabels": false,
        "showThresholdMarkers": true
      },
      "pluginVersion": "11.0.0",
      "targets": [
        {
          "expr": "sum(count_over_time({service_name=~\".*\"} |~ \"(?i)sanitized|redacted\" [1h]))",
          "refId": "A"
        }
      ],
      "title": "Items Sanitized (Last Hour)",
      "type": "gauge"
    },
    {
      "datasource": "Loki",
      "fieldConfig": {
        "defaults": {
          "color": {
            "mode": "thresholds"
          },
          "mappings": [],
          "thresholds": {
            "mode": "absolute",
            "steps": [
              {
                "color": "green",
                "value": null
              },
              {
                "color": "red",
                "value": 1
              }
            ]
          }
        },
        "overrides": []
      },
      "gridPos": {
        "h": 8,
        "w": 8,
        "x": 16,
        "y": 0
      },
      "id": 3,
      "options": {
        "orientation": "auto",
        "reduceOptions": {
          "values": false,
          "calcs": [
            "lastNotNull"
          ],
          "fields": ""
        },
        "showThresholdLabels": false,
        "showThresholdMarkers": true
      },
      "pluginVersion": "11.0.0",
      "targets": [
        {
          "expr": "sum(count_over_time({service_name=~\".*\"} |~ \"(?i)compliance.*violation\" [24h]))",
          "refId": "A"
        }
      ],
      "title": "Compliance Violations (24h)",
      "type": "gauge"
    },
    {
      "datasource": "Loki",
      "fieldConfig": {
        "defaults": {
          "color": {
            "mode": "palette-classic"
          },
          "custom": {
            "hideFrom": {
              "legend": false,
              "tooltip": false,
              "vis": false
            }
          },
          "mappings": []
        },
        "overrides": []
      },
      "gridPos": {
        "h": 8,
        "w": 12,
        "x": 0,
        "y": 8
      },
      "id": 4,
      "options": {
        "legend": {
          "displayMode": "table",
          "placement": "right",
          "values": [
            "value",
            "percent"
          ]
        },
        "pieType": "pie",
        "reduceOptions": {
          "values": false,
          "calcs": [
            "lastNotNull"
          ],
          "fields": ""
        },
        "tooltip": {
          "mode": "single"
        }
      },
      "targets": [
        {
          "expr": "sum by (pii_type) (count_over_time({service_name=~\".*\"} | json | pii_type != \"\" [6h]))",
          "refId": "A"
        }
      ],
      "title": "PII Types Detected",
      "type": "piechart"
    },
    {
      "datasource": "Loki",
      "fieldConfig": {
        "defaults": {
          "color": {
            "mode": "palette-classic"
          },
          "custom": {
            "axisLabel": "",
            "axisPlacement": "auto",
            "barAlignment": 0,
            "drawStyle": "line",
            "fillOpacity": 10,
            "gradientMode": "none",
            "hideFrom": {
              "legend": false,
              "tooltip": false,
              "vis": false
            },
            "lineInterpolation": "linear",
            "lineWidth": 1,
            "pointSize": 5,
            "scaleDistribution": {
              "type": "linear"
            },
            "showPoints": "never",
            "spanNulls": false,
            "stacking": {
              "group": "A",
              "mode": "none"
            },
            "thresholdsStyle": {
              "mode": "off"
            }
          },
          "mappings": [],
          "thresholds": {
            "mode": "absolute",
            "steps": [
              {
                "color": "green",
                "value": null
              },
              {
                "color": "red",
                "value": 80
              }
            ]
          },
          "unit": "short"
        },
        "overrides": []
      },
      "gridPos": {
        "h": 8,
        "w": 12,
        "x": 12,
        "y": 8
      },
      "id": 5,
      "options": {
        "legend": {
          "calcs": [],
          "displayMode": "list",
          "placement": "bottom"
        },
        "tooltip": {
          "mode": "single"
        }
      },
      "targets": [
        {
          "expr": "sum(count_over_time({service_name=~\".*\"} |~ \"(?i)pii.*detected\" [10m])) by (bin(10m))",
          "refId": "A",
          "legendFormat": "PII Detections"
        },
        {
          "expr": "sum(count_over_time({service_name=~\".*\"} |~ \"(?i)sanitized\" [10m])) by (bin(10m))",
          "refId": "B",
          "legendFormat": "Items Sanitized"
        }
      ],
      "title": "PII Detection Trends",
      "type": "timeseries"
    },
    {
      "datasource": "Loki",
      "fieldConfig": {
        "defaults": {
          "color": {
            "mode": "thresholds"
          },
          "custom": {
            "align": "auto",
            "displayMode": "auto"
          },
          "mappings": [],
          "thresholds": {
            "mode": "absolute",
            "steps": [
              {
                "color": "green",
                "value": null
              },
              {
                "color": "red",
                "value": 80
              }
            ]
          }
        },
        "overrides": [
          {
            "matcher": {
              "id": "byName",
              "options": "level"
            },
            "properties": [
              {
                "id": "custom.displayMode",
                "value": "color-background"
              }
            ]
          }
        ]
      },
      "gridPos": {
        "h": 8,
        "w": 24,
        "x": 0,
        "y": 16
      },
      "id": 6,
      "options": {
        "showHeader": true
      },
      "pluginVersion": "11.0.0",
      "targets": [
        {
          "expr": "{service_name=~\".*\"} |~ \"(?i)pii|sanitiz|redact|compliance\" | json | __error__ = \"\"",
          "refId": "A"
        }
      ],
      "title": "Recent PII/Compliance Activity",
      "type": "table"
    }
  ],
  "refresh": "30s",
  "schemaVersion": 27,
  "style": "dark",
  "tags": ["sting", "pii", "compliance", "security"],
  "templating": {
    "list": []
  },
  "time": {
    "from": "now-6h",
    "to": "now"
  },
  "timepicker": {},
  "timezone": "",
  "title": "STING PII Compliance Dashboard",
  "version": 1
}